ntpfixtime/__init__.py
ntpfixtime/api.py
ntpfixtime-0.0.6.dist-info/DESCRIPTION.rst
ntpfixtime-0.0.6.dist-info/METADATA
ntpfixtime-0.0.6.dist-info/RECORD
ntpfixtime-0.0.6.dist-info/WHEEL
ntpfixtime-0.0.6.dist-info/metadata.json
ntpfixtime-0.0.6.dist-info/top_level.txt
